osc_gen/__init__.py
osc_gen/dsp.py
osc_gen/sig.py
osc_gen/visualize.py
osc_gen/wavetable.py
osc_gen/wavfile.py
osc_gen/zosc.py
osc_gen-1.3.3.dist-info/LICENSE
osc_gen-1.3.3.dist-info/METADATA
osc_gen-1.3.3.dist-info/WHEEL
osc_gen-1.3.3.dist-info/top_level.txt
osc_gen-1.3.3.dist-info/RECORD
