Metadata-Version: 2.1
Name: osc-gen
Version: 1.3.3
Summary: Generate oscilator wavetoables
Home-page: https://github.com/harveyormston/osc_gen
Author: Harvey Ormston
Author-email: harveyormston@me.com
License: GPL3
Keywords: audio dsp synthsis
Platform: UNKNOWN
Classifier: Development Status :: 4 - Beta
Classifier: Intended Audience :: Developers
Classifier: Topic :: Multimedia :: Sound/Audio
Classifier: Topic :: Multimedia :: Sound/Audio :: Analysis
Classifier: Topic :: Multimedia :: Sound/Audio :: Sound Synthesis
Classifier: License :: OSI Approved :: GNU General Public License v3 (GPLv3)
Classifier: Programming Language :: Python :: 2
Classifier: Programming Language :: Python :: 2.7
Classifier: Programming Language :: Python :: 3
Classifier: Programming Language :: Python :: 3.5
Classifier: Programming Language :: Python :: 3.6
Requires-Python: >=2.7, !=3.0.*, !=3.1.*, !=3.2.*, !=3.3.*, !=3.4.*, <4
Requires-Dist: numpy (>=1.11.3)
Requires-Dist: scipy (>=0.18.1)
Requires-Dist: pysoundfile
